txl/__init__.py
txl/app.py
txl/base.py
txl/cli.py
txl/text_input.py
txl-0.3.2.dist-info/METADATA
txl-0.3.2.dist-info/WHEEL
txl-0.3.2.dist-info/licenses/LICENSE.txt
txl-0.3.2.dist-info/RECORD
